verilog/testbenchende.v

//Module to implement a 4 bit counter=> Each time it reaches 8 it return one
module counter4Bit(clock, isItEight);
	
	input 		clock;
	output reg	isItEight;					//Every eight cycle we need to load into the registers in the PISO

	integer i = 0;
	
	always @ (posedge clock)
	begin
		if (i == 0)
			isItEight = 0;
		i = i + 1;
		if(i == 9)
		begin
			i = 0;
			isItEight = 0;
		end
		
		else if(i==8)
		begin
			isItEight = 1;
		end	

	end
endmodule

//Module to implement PISO
module PISO(clock, message, serialOut);

	input		clock;
	input [7:0] 	message; 
	output reg	serialOut;

	wire		load;
	reg [7:0] 	tempMessage;
	integer 	i;

	counter4Bit	counter(.clock(clock), .isItEight(load));
	//assign serialIn = 0;
	always @ (posedge clock)
	begin
		if(load == 1)
			tempMessage = message;

		if(load == 0)
		begin
			serialOut = tempMessage[0];
			for(i = 1 ; i < 8 ; i = i + 1)
			begin
				tempMessage[i - 1] = tempMessage[i];
			end
			tempMessage[7] = 0;
			//$display ("Serial Out = %b", serialOut);
		end
	end
endmodule

`timescale 1ns / 1ps

module testbench;

	reg		clock;
	reg [7:0]	message;
	wire 		serialOut;

	initial
        begin
        	clock = 1; 
        end
   	always #1 clock = ~clock;

	PISO	tester(.clock(clock), .message(message), .serialOut(serialOut));

	initial 
	begin
	$dumpfile("16CO128-V2.vcd");
	$dumpvars(0,testbench);

	message = 8'b00001111;
	#50 $finish;

	end

	/*initial begin
		$monitor("\nTime = %d Serial out = %d", $time,  serialOut);
	end*/
endmodule

verilog/16CO128-V2.vcd
$date
	Tue Nov  7 01:27:45 2017
$end
$version
	Icarus Verilog
$end
$timescale
	1ps
$end
$scope module testbench $end
$var wire 1 ! serialOut $end
$var reg 1 " clock $end
$var reg 8 # message [7:0] $end
$scope module tester $end
$var wire 1 $ clock $end
$var wire 1 % load $end
$var wire 8 & message [7:0] $end
$var integer 32 ' i [31:0] $end
$var reg 1 ( serialOut $end
$var reg 8 ) tempMessage [7:0] $end
$scope module counter $end
$var wire 1 $ clock $end
$var integer 32 * i [31:0] $end
$var reg 1 + isItEight $end
$upscope $end
$upscope $end
$upscope $end
$enddefinitions $end
#0
$dumpvars
0+
b1 *
bx )
x(
bx '
b1111 &
0%
1$
b1111 #
1"
x!
$end
#1000
0"
0$
#2000
b0xxxxxxx )
b1000 '
b10 *
1"
1$
#3000
0"
0$
#4000
b11 *
b0xxxxxx )
b1000 '
1"
1$
#5000
0"
0$
#6000
b0xxxxx )
b1000 '
b100 *
1"
1$
#7000
0"
0$
#8000
b101 *
b0xxxx )
b1000 '
1"
1$
#9000
0"
0$
#10000
b0xxx )
b1000 '
b110 *
1"
1$
#11000
0"
0$
#12000
b111 *
b0xx )
b1000 '
1"
1$
#13000
0"
0$
#14000
b1111 )
1+
1%
b1000 *
1"
1$
#15000
0"
0$
#16000
0+
0%
b0 *
1"
1$
#17000
0"
0$
#18000
b111 )
b1000 '
1(
1!
b1 *
1"
1$
#19000
0"
0$
#20000
b10 *
b11 )
b1000 '
1"
1$
#21000
0"
0$
#22000
b1 )
b1000 '
b11 *
1"
1$
#23000
0"
0$
#24000
b100 *
b0 )
b1000 '
1"
1$
#25000
0"
0$
#26000
b0 )
b1000 '
0(
0!
b101 *
1"
1$
#27000
0"
0$
#28000
b110 *
b0 )
b1000 '
1"
1$
#29000
0"
0$
#30000
b0 )
b1000 '
b111 *
1"
1$
#31000
0"
0$
#32000
1+
1%
b1000 *
b0 )
b1000 '
1"
1$
#33000
0"
0$
#34000
b0 )
b1000 '
0+
0%
b0 *
1"
1$
#35000
0"
0$
#36000
b1 *
b0 )
b1000 '
1"
1$
#37000
0"
0$
#38000
b0 )
b1000 '
b10 *
1"
1$
#39000
0"
0$
#40000
b11 *
b0 )
b1000 '
1"
1$
#41000
0"
0$
#42000
b0 )
b1000 '
b100 *
1"
1$
#43000
0"
0$
#44000
b101 *
b0 )
b1000 '
1"
1$
#45000
0"
0$
#46000
b0 )
b1000 '
b110 *
1"
1$
#47000
0"
0$
#48000
b111 *
b0 )
b1000 '
1"
1$
#49000
0"
0$
#50000
b1111 )
1+
1%
b1000 *
1"
1$
